pyserverses/__init__.py
pyserverses/client.py
pyserverses/server.py
pyserverses/utils.py
pyserverses-0.1.2.dist-info/METADATA
pyserverses-0.1.2.dist-info/WHEEL
pyserverses-0.1.2.dist-info/top_level.txt
pyserverses-0.1.2.dist-info/RECORD
