Metadata-Version: 2.4
Name: pyserverses
Version: 0.1.2
Summary: Простая библиотека для создания серверов и клиентов
Home-page: https://github.com/koteey/pyserverses
Author: kote
Author-email: arturzavalov64@gmail.com
Classifier: Programming Language :: Python :: 3
Classifier: License :: OSI Approved :: MIT License
Classifier: Operating System :: OS Independent
Requires-Python: >=3.6
Dynamic: author
Dynamic: author-email
Dynamic: classifier
Dynamic: description-content-type
Dynamic: home-page
Dynamic: requires-python
Dynamic: summary
